gateaux/__init__.py
gateaux/errors.py
gateaux/structure.py
gateaux/fields/__init__.py
gateaux/fields/base.py
gateaux/fields/binary.py
gateaux/fields/boolean.py
gateaux/fields/datetime.py
gateaux/fields/enum.py
gateaux/fields/float.py
gateaux/fields/integer.py
gateaux/fields/ipv4address.py
gateaux/fields/ipv4network.py
gateaux/fields/ipv6address.py
gateaux/fields/ipv6network.py
gateaux/fields/string.py
gateaux/fields/uuid.py
gateaux-0.2.dist-info/LICENSE
gateaux-0.2.dist-info/METADATA
gateaux-0.2.dist-info/WHEEL
gateaux-0.2.dist-info/top_level.txt
gateaux-0.2.dist-info/RECORD
