Metadata-Version: 2.1
Name: gateaux
Version: 0.2
Summary: Typed data structures for FoundationDB.
Home-page: https://github.com/meeb/gateaux
Author: https://github.com/meeb
Author-email: meeb@meeb.org
License: MIT
Keywords: gateaux,foundationdb,fdb,data,structure,structures,typed,typing
Platform: UNKNOWN
Classifier: Development Status :: 5 - Production/Stable
Classifier: Environment :: Web Environment
Classifier: Intended Audience :: Developers
Classifier: License :: OSI Approved :: MIT License
Classifier: Operating System :: OS Independent
Classifier: Programming Language :: Python
Classifier: Programming Language :: Python :: 3
Classifier: Programming Language :: Python :: 3.6
Classifier: Topic :: Software Development :: Libraries :: Application Frameworks
Classifier: Topic :: Software Development :: Libraries :: Python Modules
Requires-Dist: foundationdb
Requires-Dist: pytz
